vantage/VERSION
vantage/__init__.py
vantage/constants.py
vantage/utest.py
vantage/_data/example_fixtures.yaml
vantage/_data/node_config_skeleton.yaml
vantage/_data/server_config_skeleton.yaml
vantage/_data/testnodeconfiguration.yaml
vantage/_data/unittest_config.yaml
vantage/_data/dev/fixtures.yaml
vantage/_data/dev/node_a.yaml
vantage/_data/dev/node_b.yaml
vantage/_data/dev/server.yaml
vantage/node/__init__.py
vantage/node/docker_manager.py
vantage/node/encryption.py
vantage/node/proxy_server.py
vantage/node/server_io.py
vantage/node/start.py
vantage/node_manager/__init__.py
vantage/node_manager/cli/__init__.py
vantage/node_manager/cli/node_manager.py
vantage/server/__init__.py
vantage/server/db.py
vantage/server/server.wsgi
vantage/server/shell.py
vantage/server/websockets.py
vantage/server/cli/__init__.py
vantage/server/cli/server.py
vantage/server/controller/__init__.py
vantage/server/controller/fixture.py
vantage/server/controller/query.py
vantage/server/model/__init__.py
vantage/server/model/authenticable.py
vantage/server/model/base.py
vantage/server/model/collaboration.py
vantage/server/model/member.py
vantage/server/model/node.py
vantage/server/model/organization.py
vantage/server/model/result.py
vantage/server/model/task.py
vantage/server/model/user.py
vantage/server/resource/__init__.py
vantage/server/resource/_schema.py
vantage/server/resource/collaboration.py
vantage/server/resource/node.py
vantage/server/resource/organization.py
vantage/server/resource/result.py
vantage/server/resource/stats.py
vantage/server/resource/task.py
vantage/server/resource/token.py
vantage/server/resource/user.py
vantage/server/resource/version.py
vantage/server/resource/websocket_test.py
vantage/server/resource/swagger/__init__.py
vantage/server/resource/swagger/delete_collaboration_node.yaml
vantage/server/resource/swagger/delete_collaboration_organization.yaml
vantage/server/resource/swagger/delete_collaboration_task.yaml
vantage-0.3.0a5.dist-info/LICENSE
vantage-0.3.0a5.dist-info/METADATA
vantage-0.3.0a5.dist-info/WHEEL
vantage-0.3.0a5.dist-info/entry_points.txt
vantage-0.3.0a5.dist-info/top_level.txt
vantage-0.3.0a5.dist-info/RECORD
