Metadata-Version: 2.1
Name: vantage
Version: 0.3.0a5
Summary: Package and utilities for distributed learning
Home-page: https://github.com/IKNL/vantage
License: UNKNOWN
Platform: UNKNOWN
Requires-Python: >=3
Requires-Dist: appdirs
Requires-Dist: bcrypt
Requires-Dist: click
Requires-Dist: colorama
Requires-Dist: docker
Requires-Dist: eventlet
Requires-Dist: flask
Requires-Dist: flask-cors
Requires-Dist: flask-jwt-extended
Requires-Dist: flask-restful
Requires-Dist: flask-sqlalchemy
Requires-Dist: flask-marshmallow
Requires-Dist: flask-socketio
Requires-Dist: socketIO-client
Requires-Dist: marshmallow (==2.16.3)
Requires-Dist: marshmallow-sqlalchemy (==0.15.0)
Requires-Dist: pyyaml
Requires-Dist: psutil
Requires-Dist: psycopg2-binary
Requires-Dist: requests
Requires-Dist: termcolor
Requires-Dist: sqlalchemy
Requires-Dist: iknl-flasgger
Requires-Dist: schema
Requires-Dist: questionary
Requires-Dist: ipython
Requires-Dist: cryptography
Requires-Dist: gevent
